odoo/addons/website_logo/README.rst
odoo/addons/website_logo/__init__.py
odoo/addons/website_logo/__manifest__.py
odoo/addons/website_logo/i18n/ca.po
odoo/addons/website_logo/i18n/ca_ES.po
odoo/addons/website_logo/i18n/es.po
odoo/addons/website_logo/i18n/fr.po
odoo/addons/website_logo/i18n/it.po
odoo/addons/website_logo/i18n/pt_BR.po
odoo/addons/website_logo/i18n/website_logo.pot
odoo/addons/website_logo/models/__init__.py
odoo/addons/website_logo/models/res_config.py
odoo/addons/website_logo/models/website.py
odoo/addons/website_logo/readme/CONFIGURE.rst
odoo/addons/website_logo/readme/CONTRIBUTORS.rst
odoo/addons/website_logo/readme/DESCRIPTION.rst
odoo/addons/website_logo/readme/ROADMAP.rst
odoo/addons/website_logo/readme/USAGE.rst
odoo/addons/website_logo/static/description/icon.png
odoo/addons/website_logo/static/description/index.html
odoo/addons/website_logo/views/res_config_view.xml
odoo/addons/website_logo/views/website_templates.xml
odoo12_addon_website_logo-12.0.1.0.0.99.dev16.dist-info/METADATA
odoo12_addon_website_logo-12.0.1.0.0.99.dev16.dist-info/WHEEL
odoo12_addon_website_logo-12.0.1.0.0.99.dev16.dist-info/top_level.txt
odoo12_addon_website_logo-12.0.1.0.0.99.dev16.dist-info/RECORD
